[
  {
    "name": "Alpha Plumbing Repair LLC",
    "legalName": "Alpha Plumbing Repair LLC",
    "specialty": "Plumbing",
    "searchQuery": "\"Alpha Plumbing Repair LLC\" contractor contact information phone address website"
  },
  {
    "name": "DT Construction LLC",
    "legalName": "DT Construction LLC",
    "specialty": "General Construction",
    "searchQuery": "\"DT Construction LLC\" contractor contact information phone address website"
  },
  {
    "name": "Performance Foam Tech Inc",
    "legalName": "Performance Foam Tech Inc",
    "specialty": "Contractor Services",
    "searchQuery": "\"Performance Foam Tech Inc\" contractor contact information phone address website"
  },
  {
    "name": "Twenty Eight Builders Inc",
    "legalName": "Twenty Eight Builders Inc",
    "specialty": "General Construction",
    "searchQuery": "\"Twenty Eight Builders Inc\" contractor contact information phone address website"
  },
  {
    "name": "MidState Roofing LLC",
    "legalName": "MidState Roofing LLC",
    "specialty": "Roofing",
    "searchQuery": "\"MidState Roofing LLC\" contractor contact information phone address website"
  },
  {
    "name": "Seamless Gutter Pros LLC",
    "legalName": "Seamless Gutter Pros LLC",
    "specialty": "Contractor Services",
    "searchQuery": "\"Seamless Gutter Pros LLC\" contractor contact information phone address website"
  },
  {
    "name": "Spray Foam Insulators",
    "legalName": "Spray Foam Insulators",
    "specialty": "Spray Foam Insulation",
    "searchQuery": "\"Spray Foam Insulators\" contractor contact information phone address website"
  },
  {
    "name": "Air Tight Spray Foam of Pensacola LLC",
    "legalName": "Air Tight Spray Foam of Pensacola LLC",
    "specialty": "Spray Foam Insulation",
    "searchQuery": "\"Air Tight Spray Foam of Pensacola LLC\" contractor contact information phone address website"
  },
  {
    "name": "Cobb Construction LLC",
    "legalName": "Cobb Construction LLC",
    "specialty": "General Construction",
    "searchQuery": "\"Cobb Construction LLC\" contractor contact information phone address website"
  },
  {
    "name": "J&J Masonry Inc",
    "legalName": "J&J Masonry Inc",
    "specialty": "Contractor Services",
    "searchQuery": "\"J&J Masonry Inc\" contractor contact information phone address website"
  }
]